distancia/__init__.py
distancia/distancia.py
distancia/fileDistance.py
distancia/graphDistance.py
distancia/imageDistance.py
distancia/lossFunction.py
distancia/mainClass.py
distancia/markovChain.py
distancia/matrixDistance.py
distancia/soundDistance.py
distancia/textDistance.py
distancia/timeSeriesDistance.py
distancia/tools.py
distancia/vectorDistance.pxd
distancia/vectorDistance.py
distancia-0.0.85.dist-info/LICENSE.txt
distancia-0.0.85.dist-info/METADATA
distancia-0.0.85.dist-info/WHEEL
distancia-0.0.85.dist-info/top_level.txt
distancia-0.0.85.dist-info/RECORD
