Metadata-Version: 2.1
Name: distancia
Version: 0.0.85
Summary: distance metrics
Home-page: https://pypi.org/project/distancia/
Author: Yves Mercadier
Author-email: Yves Mercadier <info@realpython.com>
License: LICENSE.txt
Project-URL: Homepage, https://pypi.org/project/distancia/
Keywords: distance,similarity,metrics,space,data-science,deep-learning,machine-learning,neural-network,statistics,python,cython,jupyter-notebook,data-analyse,nlp,vector,matrix,graph,markov chain,image,sound,text
Classifier: License :: OSI Approved :: MIT License
Classifier: Programming Language :: Python :: 3
Requires-Python: >=3.0
License-File: LICENSE.txt
Provides-Extra: all
Requires-Dist: flask>=2.0.0; extra == "all"
Requires-Dist: gensim>=4.0.0; extra == "all"
Requires-Dist: matplotlib>=3.5.0; extra == "all"
Requires-Dist: networkx>=2.0; extra == "all"
Requires-Dist: numpy>=1.21.0; extra == "all"
Requires-Dist: opencv-python; extra == "all"
Requires-Dist: opencv-python>=4.0.0; extra == "all"
Requires-Dist: pandas>=1.0.0; extra == "all"
Requires-Dist: pillow>=8.0.0; extra == "all"
Requires-Dist: requests>=2.0.0; extra == "all"
Requires-Dist: scikit-learn>=1.0.0; extra == "all"
Requires-Dist: scipy>=1.7.0; extra == "all"
Requires-Dist: seaborn>=0.11.0; extra == "all"
Requires-Dist: torch>=1.9.0; extra == "all"
Requires-Dist: transformers>=4.0.0; extra == "all"
Provides-Extra: flask
Requires-Dist: flask>=2.0.0; extra == "flask"
Provides-Extra: gensim
Requires-Dist: gensim>=4.0.0; extra == "gensim"
Provides-Extra: matplotlib
Requires-Dist: matplotlib>=3.5.0; extra == "matplotlib"
Provides-Extra: networkx
Requires-Dist: networkx>=2.0; extra == "networkx"
Provides-Extra: numpy
Requires-Dist: numpy>=1.21.0; extra == "numpy"
Provides-Extra: opencv
Requires-Dist: opencv-python>=4.0.0; extra == "opencv"
Provides-Extra: opencv-python
Requires-Dist: opencv-python; extra == "opencv-python"
Requires-Dist: opencv-python>=4.0.0; extra == "opencv-python"
Provides-Extra: pandas
Requires-Dist: pandas>=1.0.0; extra == "pandas"
Provides-Extra: pillow
Requires-Dist: pillow>=8.0.0; extra == "pillow"
Provides-Extra: requests
Requires-Dist: requests>=2.0.0; extra == "requests"
Provides-Extra: scikit-learn
Requires-Dist: scikit-learn>=1.0.0; extra == "scikit-learn"
Provides-Extra: scipy
Requires-Dist: scipy>=1.7.0; extra == "scipy"
Provides-Extra: seaborn
Requires-Dist: seaborn>=0.11.0; extra == "seaborn"
Provides-Extra: sklearn
Requires-Dist: scikit-learn>=1.0.0; extra == "sklearn"
Provides-Extra: torch
Requires-Dist: torch>=1.9.0; extra == "torch"
Provides-Extra: transformers
Requires-Dist: transformers>=4.0.0; extra == "transformers"
